setup.py
distributions/Binomialdistribution.py
distributions/Gaussiandistribution.py
distributions/Generaldistribution.py
distributions/__init__.py
ssdp_distributions.egg-info/PKG-INFO
ssdp_distributions.egg-info/SOURCES.txt
ssdp_distributions.egg-info/dependency_links.txt
ssdp_distributions.egg-info/not-zip-safe
ssdp_distributions.egg-info/top_level.txt